phrlibrary/__init__.py
phrlibrary/core.py
phrlibrary-1.0.2.data/scripts/custom_scripts.py
phrlibrary-1.0.2.dist-info/METADATA
phrlibrary-1.0.2.dist-info/WHEEL
phrlibrary-1.0.2.dist-info/entry_points.txt
phrlibrary-1.0.2.dist-info/top_level.txt
phrlibrary-1.0.2.dist-info/RECORD
