Metadata-Version: 2.1
Name: phrlibrary
Version: 1.0.2
Summary: A demo library
Author: Phr
Requires-Python: >=3.6
